tasks3/__init__.py
tasks3/cli.py
tasks3/config.py
tasks3/tasks3.py
tasks3/db/__init__.py
tasks3/db/db.py
tasks3/db/extension.py
tasks3/db/models.py
tasks3-0.9.1.dist-info/AUTHORS.rst
tasks3-0.9.1.dist-info/LICENSE
tasks3-0.9.1.dist-info/METADATA
tasks3-0.9.1.dist-info/WHEEL
tasks3-0.9.1.dist-info/entry_points.txt
tasks3-0.9.1.dist-info/top_level.txt
tasks3-0.9.1.dist-info/RECORD
