Metadata-Version: 2.2
Name: tasks3
Version: 0.9.1
Summary: A commandline tool to create and manage tasks and todos.
Home-page: https://github.com/hXtreme/tasks3
Author: Harsh Parekh
Author-email: harsh_parekh@outlook.com
License: GNU General Public License v3
Keywords: tasks3
Classifier: Development Status :: 3 - Alpha
Classifier: Intended Audience :: End Users/Desktop
Classifier: License :: OSI Approved :: GNU General Public License v3 (GPLv3)
Classifier: Natural Language :: English
Classifier: Programming Language :: Python :: 3
Classifier: Programming Language :: Python :: 3.12
Classifier: Programming Language :: Python :: 3.13
Requires-Python: >=3.12
License-File: LICENSE
License-File: AUTHORS.rst
Requires-Dist: Click==8.1.6
Requires-Dist: ruamel.yaml==0.18.6
Requires-Dist: SQLAlchemy==2.0.36
Dynamic: author
Dynamic: author-email
Dynamic: classifier
Dynamic: description
Dynamic: home-page
Dynamic: keywords
Dynamic: license
Dynamic: requires-dist
Dynamic: requires-python
Dynamic: summary
